{
    "shared": {
        "MONGO_HOSTNAME": "mongodb",
        "MONGO_PORT": "27017",
        "MONGO_DBNAME": "appdb",
        "MONGO_USERNAME": "appuser",
        "MONGO_PASSWORD": "secret123"
    },
    "services": {
        "worklog": {
            "HTTP_PORT": "9081",
            "HTTPS_PORT": "9444"
        },
        "notification": {
            "HTTP_PORT": "9080",
            "HTTPS_PORT": "9443"
        },
        "task": {
            "HTTP_PORT": "9082",
            "HTTPS_PORT": "9445"
        }
    },
    "frontend": {
        "NEXT_PUBLIC_WORKLOGS_API_URL": "http://localhost:7002/worklog/api"
    },
    "mongodb": {
        "MONGO_INITDB_ROOT_USERNAME": "admin",
        "MONGO_INITDB_ROOT_PASSWORD": "secret123",
        "MONGO_INITDB_DATABASE": "appdb"
    }
}